apimatic_core_interfaces/__init__.py
apimatic_core_interfaces/client/__init__.py
apimatic_core_interfaces/client/http_client.py
apimatic_core_interfaces/factories/__init__.py
apimatic_core_interfaces/factories/response_factory.py
apimatic_core_interfaces/types/__init__.py
apimatic_core_interfaces/types/authentication.py
apimatic_core_interfaces/types/http_method_enum.py
apimatic_core_interfaces-0.1.3.dist-info/LICENSE
apimatic_core_interfaces-0.1.3.dist-info/METADATA
apimatic_core_interfaces-0.1.3.dist-info/WHEEL
apimatic_core_interfaces-0.1.3.dist-info/top_level.txt
apimatic_core_interfaces-0.1.3.dist-info/RECORD
