Metadata-Version: 2.1
Name: apimatic-core-interfaces
Version: 0.1.3
Summary: An abstract layer of the functionalities provided by apimatic-core-library, requests-client-adapter and APIMatic SDKs.
Home-page: https://github.com/apimatic/core-interfaces-python
Author: APIMatic
Author-email: support@apimatic.io
License: MIT
License-File: LICENSE
